Workbook

Sheet Dashboard
B2: Dashboard de Projeção Financeira

Sheet Resumo Executivo
A1: PROJEÇÃO FINANCEIRA UNIFICADA — CRM
A3: Indicador | B3: Valor | C3: Observação
A4: Clientes ativos finais | B4: 345 | C4: Meta dez/2027
A5: MRR final | B5: 120750 | C5: Meta financeira do PDF
A6: Clientes brutos necessários | B6: 403 | C6: Com churn base de 3%
A7: Pró-labore desenvolvimento | B7: 2500 | C7: A partir de 30 clientes
A8: Resultado dez/2027 antes impostos | B8: 57904.959 | C8: Cenário-base
A9: Resultado dez/2027 após reserva 8% | B9: 48244.959 | C9: Reserva gerencial
A11: IMPORTANTE | B11: CAC, churn, conversão de listas, mix de planos e reserva fiscal são premissas de planejamento e devem ser substituídos por dados reais conforme houver histórico.

Sheet Projeção Mensal
A1: Mês | B1: Clientes ativos | C1: Churn | D1: Novos líquidos meta | E1: Novos brutos necessários | F1: MRR meta | G1: MRR Aluguel | H1: MRR Pacotes | I1: MRR Total | J1: Receita empresa após regra 1ª/2ª | K1: Comissão vendas | L1: Comissão suporte | M1: Novos via tráfego | N1: CAC tráfego | O1: Investimento tráfego | P1: Novos via lista | Q1: Contatos frios | R1: Custo lista fria | S1: Novos via influencer | T1: Custo 1ª parcela influencer | U1: Custo recorrente influencer | V1: Pró-labore desenvolvimento | W1: Pró-labore gestor comercial | X1: Pró-labore marketing | Y1: Pró-labore financeiro | Z1: Suporte fixo | AA1: Apoio técnico | AB1: SDR | AC1: Marketing/criação | AD1: Bônus metas | AE1: Infraestrutura | AF1: Impostos 8% | AG1: Resultado Bruto | AH1: Resultado Líquido | AI1: Receita Caixa | AJ1: Impostos Caixa 8% | AK1: Resultado Caixa | AL1: Saldo de Caixa Acumulado | AM1: Taxas de Pagamento
A2: Sep/2026 | B2: 5 | C2: 0 | D2: 5 | E2: =D2+C2 -> 5 | F2: =B2*Premissas!$B$3 -> 1660 | G2: {=IF(DATE(RIGHT(A2, 4), MATCH(LEFT(A2, 3), {"Jan","Feb","Mar","Apr","May","Jun","Jul","Aug","Sep","Oct","Nov","Dec"}, 0), 1) >= Aluguel!$G$2, B2 * Aluguel!$B$2 * Aluguel!$E$2, 0)} -> 0 | H2: {=SUMPRODUCT('Pacotes adicionais'!$C$2:$C$5, 'Pacotes adicionais'!$D$2:$D$5, --(DATE(RIGHT(A2, 4), MATCH(LEFT(A2, 3), {"Jan","Feb","Mar","Apr","May","Jun","Jul","Aug","Sep","Oct","Nov","Dec"}, 0), 1) >= 'Pacotes adicionais'!$F$2:$F$5)) * B2} -> 18.4925 | I2: =F2 + G2 + H2 -> 1678.4925 | J2: =I2-K2-L2 -> 587.47238 | K2: =IF($A2="", "", IFERROR($E2 * ($I2/$B2) * Premissas!$B$6, 0)) -> 839.24625 | L2: =IF($A2="", "", IFERROR($E2 * Premissas!$B$4 * ($I2/$B2) * Premissas!$B$7, 0)) -> 251.77388 | M2: =E2*'Aquisição'!$B$2 -> 3 | N2: 250 | O2: =M2*N2 -> 750 | P2: =E2*'Aquisição'!$B$3 -> 1.25 | Q2: =P2/Premissas!$B$9 -> 62.5 | R2: =Q2*Premissas!$B$8 -> 31.25 | S2: =E2*'Aquisição'!$B$4 -> 0.75 | T2: =S2*Premissas!$B$3*Premissas!$B$13 -> 199.2 | U2: =SUM($S$2:$S2)*(1-Premissas!$B$2)^(ROW()-2)*Premissas!$B$3*Premissas!$B$10 -> 24.9 | V2: =IF($B2>='Equipe e Remuneração'!$D$6, 'Equipe e Remuneração'!$C$6, 0) -> 0 | W2: =IF($B2>='Equipe e Remuneração'!$D$3, 'Equipe e Remuneração'!$C$3, 0) -> 0 | X2: =IF($B2>='Equipe e Remuneração'!$D$5, 'Equipe e Remuneração'!$C$5, 0) -> 0 | Y2: =IF($B2>='Equipe e Remuneração'!$D$7, 'Equipe e Remuneração'!$C$7, 0) -> 0 | Z2: =IF($B2>='Equipe e Remuneração'!$D$9+120, 'Equipe e Remuneração'!$C$9*3, IF($B2>='Equipe e Remuneração'!$D$9+60, 'Equipe e Remuneração'!$C$9*2, IF($B2>='Equipe e Remuneração'!$D$9, 'Equipe e Remuneração'!$C$9, 0))) -> 0 | AA2: =IF($B2>='Equipe e Remuneração'!$D$10+120, 'Equipe e Remuneração'!$C$10+2000, IF($B2>='Equipe e Remuneração'!$D$10+60, 'Equipe e Remuneração'!$C$10+1000, IF($B2>='Equipe e Remuneração'!$D$10, 'Equipe e Remuneração'!$C$10, 0))) -> 0 | AB2: =IF($B2>='Equipe e Remuneração'!$D$8*2, 'Equipe e Remuneração'!$C$8*2, IF($B2>='Equipe e Remuneração'!$D$8, 'Equipe e Remuneração'!$C$8, 0)) -> 0 | AC2: =IF($B2>=280, 2500, IF($B2>=160, 1500, 0)) -> 0 | AD2: =IF($B2>=190, 1500, IF($B2>=110, 1000, IF($B2>=65, 750, IF($B2>=45, 500, IF($B2>=30, 300, 0))))) -> 0 | AE2: =IF($B2>=251, 1359.24, IF($B2>=151, 1132.7, IF($B2>=30, 906.16, 442.15))) -> 442.15 | AF2: =F2*Premissas!$B$12 -> 132.8 | AG2: =J2 - O2 - R2 - SUM(T2:AE2) - AM2 -> -927.34867 | AH2: =AG2-AF2 -> -1060.1487 | AI2: =IF($A2="", "", IFERROR(($I2 * Premissas!$B$5) + ($E2 * ($I2/$B2) * Premissas!$B$4 * 12), 0)) -> 7217.5177 | AJ2: =IF($A2="", "", $AI2 * Premissas!$B$12) -> 577.40142 | AK2: =IF($A2="", "", $AI2 - $AJ2 - $K2 - $L2 - $O2 - $R2 - $T2 - $U2 - SUM($V2:$AE2) - AM2) -> 4034.2752 | AL2: =AK2 -> 4034.2752 | AM2: =IF($A2="", "", $B2 * 'Taxas de pagamento'!$B$12 + $AI2 * 'Taxas de pagamento'!$C$13) -> 67.321047
A3: Oct/2026 | B3: =B2+D3 -> 12 | C3: =ROUND(B2*Premissas!$B$2, 0) -> 0 | D3: 7 | E3: =D3+C3 -> 7 | F3: =B3*Premissas!$B$3 -> 3984 | G3: {=IF(DATE(RIGHT(A3, 4), MATCH(LEFT(A3, 3), {"Jan","Feb","Mar","Apr","May","Jun","Jul","Aug","Sep","Oct","Nov","Dec"}, 0), 1) >= Aluguel!$G$2, B3 * Aluguel!$B$2 * Aluguel!$E$2, 0)} -> 0 | H3: {=SUMPRODUCT('Pacotes adicionais'!$C$2:$C$5, 'Pacotes adicionais'!$D$2:$D$5, --(DATE(RIGHT(A3, 4), MATCH(LEFT(A3, 3), {"Jan","Feb","Mar","Apr","May","Jun","Jul","Aug","Sep","Oct","Nov","Dec"}, 0), 1) >= 'Pacotes adicionais'!$F$2:$F$5)) * B3} -> 113.382 | I3: =F3 + G3 + H3 -> 4097.382 | J3: =I3-K3-L3 -> 1956.319 | K3: =IF($A3="", "", IFERROR($E3 * ($I3/$B3) * Premissas!$B$6, 0)) -> 1195.0698 | L3: =IF($A3="", "", IFERROR(($E3 * Premissas!$B$4 * ($I3/$B3) + $E2 * Premissas!$B$5 * ($I2/$B2)) * Premissas!$B$7, 0)) -> 945.9933 | M3: =E3*'Aquisição'!$B$2 -> 4.2 | N3: 240 | O3: =M3*N3 -> 1008 | P3: =E3*'Aquisição'!$B$3 -> 1.75 | Q3: =P3/Premissas!$B$9 -> 87.5 | R3: =Q3*Premissas!$B$8 -> 43.75 | S3: =E3*'Aquisição'!$B$4 -> 1.05 | T3: =S3*Premissas!$B$3*Premissas!$B$13 -> 278.88 | U3: =SUM($S$2:$S3)*(1-Premissas!$B$2)^(ROW()-2)*Premissas!$B$3*Premissas!$B$10 -> 57.9672 | V3: =IF($B3>='Equipe e Remuneração'!$D$6, 'Equipe e Remuneração'!$C$6, 0) -> 0 | W3: =IF($B3>='Equipe e Remuneração'!$D$3, 'Equipe e Remuneração'!$C$3, 0) -> 0 | X3: =IF($B3>='Equipe e Remuneração'!$D$5, 'Equipe e Remuneração'!$C$5, 0) -> 0 | Y3: =IF($B3>='Equipe e Remuneração'!$D$7, 'Equipe e Remuneração'!$C$7, 0) -> 0 | Z3: =IF($B3>='Equipe e Remuneração'!$D$9+120, 'Equipe e Remuneração'!$C$9*3, IF($B3>='Equipe e Remuneração'!$D$9+60, 'Equipe e Remuneração'!$C$9*2, IF($B3>='Equipe e Remuneração'!$D$9, 'Equipe e Remuneração'!$C$9, 0))) -> 0 | AA3: =IF($B3>='Equipe e Remuneração'!$D$10+120, 'Equipe e Remuneração'!$C$10+2000, IF($B3>='Equipe e Remuneração'!$D$10+60, 'Equipe e Remuneração'!$C$10+1000, IF($B3>='Equipe e Remuneração'!$D$10, 'Equipe e Remuneração'!$C$10, 0))) -> 0 | AB3: =IF($B3>='Equipe e Remuneração'!$D$8*2, 'Equipe e Remuneração'!$C$8*2, IF($B3>='Equipe e Remuneração'!$D$8, 'Equipe e Remuneração'!$C$8, 0)) -> 0 | AC3: =IF($B3>=280, 2500, IF($B3>=160, 1500, 0)) -> 0 | AD3: =IF($B3>=190, 1500, IF($B3>=110, 1000, IF($B3>=65, 750, IF($B3>=45, 500, IF($B3>=30, 300, 0))))) -> 0 | AE3: =IF($B3>=251, 1359.24, IF($B3>=151, 1132.7, IF($B3>=30, 906.16, 442.15))) -> 442.15 | AF3: =F3*Premissas!$B$12 -> 318.72 | AG3: =J3 - O3 - R3 - SUM(T3:AE3) - AM3 -> 12.434046 | AH3: =AG3-AF3 -> -306.28595 | AI3: =IF($A3="", "", IFERROR(($I3 * Premissas!$B$5) + ($E3 * ($I3/$B3) * Premissas!$B$4 * 12), 0)) -> 11472.67 | AJ3: =IF($A3="", "", $AI3 * Premissas!$B$12) -> 917.81357 | AK3: =IF($A3="", "", $AI3 - $AJ3 - $K3 - $L3 - $O3 - $R3 - $T3 - $U3 - SUM($V3:$AE3) - AM3) -> 6469.9081 | AL3: =AL2+AK3 -> 10504.183 | AM3: =IF($A3="", "", $B3 * 'Taxas de pagamento'!$B$12 + $AI3 * 'Taxas de pagamento'!$C$13) -> 113.1377
A4: Nov/2026 | B4: =B3+D4 -> 20 | C4: =ROUND(B3*Premissas!$B$2, 0) -> 0 | D4: 8 | E4: =D4+C4 -> 8 | F4: =B4*Premissas!$B$3 -> 6640 | G4: {=IF(DATE(RIGHT(A4, 4), MATCH(LEFT(A4, 3), {"Jan","Feb","Mar","Apr","May","Jun","Jul","Aug","Sep","Oct","Nov","Dec"}, 0), 1) >= Aluguel!$G$2, B4 * Aluguel!$B$2 * Aluguel!$E$2, 0)} -> 1200 | H4: {=SUMPRODUCT('Pacotes adicionais'!$C$2:$C$5, 'Pacotes adicionais'!$D$2:$D$5, --(DATE(RIGHT(A4, 4), MATCH(LEFT(A4, 3), {"Jan","Feb","Mar","Apr","May","Jun","Jul","Aug","Sep","Oct","Nov","Dec"}, 0), 1) >= 'Pacotes adicionais'!$F$2:$F$5)) * B4} -> 188.97 | I4: =F4 + G4 + H4 -> 8028.97 | J4: =I4-K4-L4 -> 5104.889 | K4: =IF($A4="", "", IFERROR($E4 * ($I4/$B4) * Premissas!$B$6, 0)) -> 1605.794 | L4: =IF($A4="", "", IFERROR(($E4 * Premissas!$B$4 * ($I4/$B4) + $E3 * Premissas!$B$5 * ($I3/$B3)) * Premissas!$B$7, 0)) -> 1318.287 | M4: =E4*'Aquisição'!$B$2 -> 4.8 | N4: 230 | O4: =M4*N4 -> 1104 | P4: =E4*'Aquisição'!$B$3 -> 2 | Q4: =P4/Premissas!$B$9 -> 100 | R4: =Q4*Premissas!$B$8 -> 50 | S4: =E4*'Aquisição'!$B$4 -> 1.2 | T4: =S4*Premissas!$B$3*Premissas!$B$13 -> 318.72 | U4: =SUM($S$2:$S4)*(1-Premissas!$B$2)^(ROW()-2)*Premissas!$B$3*Premissas!$B$10 -> 93.71364 | V4: =IF($B4>='Equipe e Remuneração'!$D$6, 'Equipe e Remuneração'!$C$6, 0) -> 0 | W4: =IF($B4>='Equipe e Remuneração'!$D$3, 'Equipe e Remuneração'!$C$3, 0) -> 0 | X4: =IF($B4>='Equipe e Remuneração'!$D$5, 'Equipe e Remuneração'!$C$5, 0) -> 0 | Y4: =IF($B4>='Equipe e Remuneração'!$D$7, 'Equipe e Remuneração'!$C$7, 0) -> 0 | Z4: =IF($B4>='Equipe e Remuneração'!$D$9+120, 'Equipe e Remuneração'!$C$9*3, IF($B4>='Equipe e Remuneração'!$D$9+60, 'Equipe e Remuneração'!$C$9*2, IF($B4>='Equipe e Remuneração'!$D$9, 'Equipe e Remuneração'!$C$9, 0))) -> 0 | AA4: =IF($B4>='Equipe e Remuneração'!$D$10+120, 'Equipe e Remuneração'!$C$10+2000, IF($B4>='Equipe e Remuneração'!$D$10+60, 'Equipe e Remuneração'!$C$10+1000, IF($B4>='Equipe e Remuneração'!$D$10, 'Equipe e Remuneração'!$C$10, 0))) -> 0 | AB4: =IF($B4>='Equipe e Remuneração'!$D$8*2, 'Equipe e Remuneração'!$C$8*2, IF($B4>='Equipe e Remuneração'!$D$8, 'Equipe e Remuneração'!$C$8, 0)) -> 0 | AC4: =IF($B4>=280, 2500, IF($B4>=160, 1500, 0)) -> 0 | AD4: =IF($B4>=190, 1500, IF($B4>=110, 1000, IF($B4>=65, 750, IF($B4>=45, 500, IF($B4>=30, 300, 0))))) -> 0 | AE4: =IF($B4>=251, 1359.24, IF($B4>=151, 1132.7, IF($B4>=30, 906.16, 442.15))) -> 442.15 | AF4: =F4*Premissas!$B$12 -> 531.2 | AG4: =J4 - O4 - R4 - SUM(T4:AE4) - AM4 -> 2923.7984 | AH4: =AG4-AF4 -> 2392.5984 | AI4: =IF($A4="", "", IFERROR(($I4 * Premissas!$B$5) + ($E4 * ($I4/$B4) * Premissas!$B$4 * 12), 0)) -> 17181.996 | AJ4: =IF($A4="", "", $AI4 * Premissas!$B$12) -> 1374.5597 | AK4: =IF($A4="", "", $AI4 - $AJ4 - $K4 - $L4 - $O4 - $R4 - $T4 - $U4 - SUM($V4:$AE4) - AM4) -> 10702.265 | AL4: =AL3+AK4 -> 21206.448 | AM4: =IF($A4="", "", $B4 * 'Taxas de pagamento'!$B$12 + $AI4 * 'Taxas de pagamento'!$C$13) -> 172.50693
A5: Dec/2026 | B5: =B4+D5 -> 30 | C5: =ROUND(B4*Premissas!$B$2, 0) -> 1 | D5: 10 | E5: =D5+C5 -> 11 | F5: =B5*Premissas!$B$3 -> 9960 | G5: {=IF(DATE(RIGHT(A5, 4), MATCH(LEFT(A5, 3), {"Jan","Feb","Mar","Apr","May","Jun","Jul","Aug","Sep","Oct","Nov","Dec"}, 0), 1) >= Aluguel!$G$2, B5 * Aluguel!$B$2 * Aluguel!$E$2, 0)} -> 1800 | H5: {=SUMPRODUCT('Pacotes adicionais'!$C$2:$C$5, 'Pacotes adicionais'!$D$2:$D$5, --(DATE(RIGHT(A5, 4), MATCH(LEFT(A5, 3), {"Jan","Feb","Mar","Apr","May","Jun","Jul","Aug","Sep","Oct","Nov","Dec"}, 0), 1) >= 'Pacotes adicionais'!$F$2:$F$5)) * B5} -> 283.455 | I5: =F5 + G5 + H5 -> 12043.455 | J5: =I5-K5-L5 -> 8049.0424 | K5: =IF($A5="", "", IFERROR($E5 * ($I5/$B5) * Premissas!$B$6, 0)) -> 2207.9668 | L5: =IF($A5="", "", IFERROR(($E5 * Premissas!$B$4 * ($I5/$B5) + $E4 * Premissas!$B$5 * ($I4/$B4)) * Premissas!$B$7, 0)) -> 1786.4458 | M5: =E5*'Aquisição'!$B$2 -> 6.6 | N5: 220 | O5: =M5*N5 -> 1452 | P5: =E5*'Aquisição'!$B$3 -> 2.75 | Q5: =P5/Premissas!$B$9 -> 137.5 | R5: =Q5*Premissas!$B$8 -> 68.75 | S5: =E5*'Aquisição'!$B$4 -> 1.65 | T5: =S5*Premissas!$B$3*Premissas!$B$13 -> 438.24 | U5: =SUM($S$2:$S5)*(1-Premissas!$B$2)^(ROW()-2)*Premissas!$B$3*Premissas!$B$10 -> 140.89846 | V5: =IF($B5>='Equipe e Remuneração'!$D$6, 'Equipe e Remuneração'!$C$6, 0) -> 2500 | W5: =IF($B5>='Equipe e Remuneração'!$D$3, 'Equipe e Remuneração'!$C$3, 0) -> 0 | X5: =IF($B5>='Equipe e Remuneração'!$D$5, 'Equipe e Remuneração'!$C$5, 0) -> 0 | Y5: =IF($B5>='Equipe e Remuneração'!$D$7, 'Equipe e Remuneração'!$C$7, 0) -> 0 | Z5: =IF($B5>='Equipe e Remuneração'!$D$9+120, 'Equipe e Remuneração'!$C$9*3, IF($B5>='Equipe e Remuneração'!$D$9+60, 'Equipe e Remuneração'!$C$9*2, IF($B5>='Equipe e Remuneração'!$D$9, 'Equipe e Remuneração'!$C$9, 0))) -> 0 | AA5: =IF($B5>='Equipe e Remuneração'!$D$10+120, 'Equipe e Remuneração'!$C$10+2000, IF($B5>='Equipe e Remuneração'!$D$10+60, 'Equipe e Remuneração'!$C$10+1000, IF($B5>='Equipe e Remuneração'!$D$10, 'Equipe e Remuneração'!$C$10, 0))) -> 0 | AB5: =IF($B5>='Equipe e Remuneração'!$D$8*2, 'Equipe e Remuneração'!$C$8*2, IF($B5>='Equipe e Remuneração'!$D$8, 'Equipe e Remuneração'!$C$8, 0)) -> 0 | AC5: =IF($B5>=280, 2500, IF($B5>=160, 1500, 0)) -> 0 | AD5: =IF($B5>=190, 1500, IF($B5>=110, 1000, IF($B5>=65, 750, IF($B5>=45, 500, IF($B5>=30, 300, 0))))) -> 300 | AE5: =IF($B5>=251, 1359.24, IF($B5>=151, 1132.7, IF($B5>=30, 906.16, 442.15))) -> 906.16 | AF5: =F5*Premissas!$B$12 -> 796.8 | AG5: =J5 - O5 - R5 - SUM(T5:AE5) - AM5 -> 1996.2 | AH5: =AG5-AF5 -> 1199.4 | AI5: =IF($A5="", "", IFERROR(($I5 * Premissas!$B$5) + ($E5 * ($I5/$B5) * Premissas!$B$4 * 12), 0)) -> 24327.779 | AJ5: =IF($A5="", "", $AI5 * Premissas!$B$12) -> 1946.2223 | AK5: =IF($A5="", "", $AI5 - $AJ5 - $K5 - $L5 - $O5 - $R5 - $T5 - $U5 - SUM($V5:$AE5) - AM5) -> 12334.302 | AL5: =AL4+AK5 -> 33540.75 | AM5: =IF($A5="", "", $B5 * 'Taxas de pagamento'!$B$12 + $AI5 * 'Taxas de pagamento'!$C$13) -> 246.79401
A6: Jan/2027 | B6: =B5+D6 -> 45 | C6: =ROUND(B5*Premissas!$B$2, 0) -> 1 | D6: 15 | E6: =D6+C6 -> 16 | F6: =B6*Premissas!$B$3 -> 14940 | G6: {=IF(DATE(RIGHT(A6, 4), MATCH(LEFT(A6, 3), {"Jan","Feb","Mar","Apr","May","Jun","Jul","Aug","Sep","Oct","Nov","Dec"}, 0), 1) >= Aluguel!$G$2, B6 * Aluguel!$B$2 * Aluguel!$E$2, 0)} -> 2700 | H6: {=SUMPRODUCT('Pacotes adicionais'!$C$2:$C$5, 'Pacotes adicionais'!$D$2:$D$5, --(DATE(RIGHT(A6, 4), MATCH(LEFT(A6, 3), {"Jan","Feb","Mar","Apr","May","Jun","Jul","Aug","Sep","Oct","Nov","Dec"}, 0), 1) >= 'Pacotes adicionais'!$F$2:$F$5)) * B6} -> 425.1825 | I6: =F6 + G6 + H6 -> 18065.182 | J6: =I6-K6-L6 -> 12344.541 | K6: =IF($A6="", "", IFERROR($E6 * ($I6/$B6) * Premissas!$B$6, 0)) -> 3211.588 | L6: =IF($A6="", "", IFERROR(($E6 * Premissas!$B$4 * ($I6/$B6) + $E5 * Premissas!$B$5 * ($I5/$B5)) * Premissas!$B$7, 0)) -> 2509.0531 | M6: =E6*'Aquisição'!$B$2 -> 9.6 | N6: 210 | O6: =M6*N6 -> 2016 | P6: =E6*'Aquisição'!$B$3 -> 4 | Q6: =P6/Premissas!$B$9 -> 200 | R6: =Q6*Premissas!$B$8 -> 100 | S6: =E6*'Aquisição'!$B$4 -> 2.4 | T6: =S6*Premissas!$B$3*Premissas!$B$13 -> 637.44 | U6: =SUM($S$2:$S6)*(1-Premissas!$B$2)^(ROW()-2)*Premissas!$B$3*Premissas!$B$10 -> 207.21164 | V6: =IF($B6>='Equipe e Remuneração'!$D$6, 'Equipe e Remuneração'!$C$6, 0) -> 2500 | W6: =IF($B6>='Equipe e Remuneração'!$D$3, 'Equipe e Remuneração'!$C$3, 0) -> 0 | X6: =IF($B6>='Equipe e Remuneração'!$D$5, 'Equipe e Remuneração'!$C$5, 0) -> 0 | Y6: =IF($B6>='Equipe e Remuneração'!$D$7, 'Equipe e Remuneração'!$C$7, 0) -> 0 | Z6: =IF($B6>='Equipe e Remuneração'!$D$9+120, 'Equipe e Remuneração'!$C$9*3, IF($B6>='Equipe e Remuneração'!$D$9+60, 'Equipe e Remuneração'!$C$9*2, IF($B6>='Equipe e Remuneração'!$D$9, 'Equipe e Remuneração'!$C$9, 0))) -> 0 | AA6: =IF($B6>='Equipe e Remuneração'!$D$10+120, 'Equipe e Remuneração'!$C$10+2000, IF($B6>='Equipe e Remuneração'!$D$10+60, 'Equipe e Remuneração'!$C$10+1000, IF($B6>='Equipe e Remuneração'!$D$10, 'Equipe e Remuneração'!$C$10, 0))) -> 0 | AB6: =IF($B6>='Equipe e Remuneração'!$D$8*2, 'Equipe e Remuneração'!$C$8*2, IF($B6>='Equipe e Remuneração'!$D$8, 'Equipe e Remuneração'!$C$8, 0)) -> 0 | AC6: =IF($B6>=280, 2500, IF($B6>=160, 1500, 0)) -> 0 | AD6: =IF($B6>=190, 1500, IF($B6>=110, 1000, IF($B6>=65, 750, IF($B6>=45, 500, IF($B6>=30, 300, 0))))) -> 500 | AE6: =IF($B6>=251, 1359.24, IF($B6>=151, 1132.7, IF($B6>=30, 906.16, 442.15))) -> 906.16 | AF6: =F6*Premissas!$B$12 -> 1195.2 | AG6: =J6 - O6 - R6 - SUM(T6:AE6) - AM6 -> 5113.5219 | AH6: =AG6-AF6 -> 3918.3219 | AI6: =IF($A6="", "", IFERROR(($I6 * Premissas!$B$5) + ($E6 * ($I6/$B6) * Premissas!$B$4 * 12), 0)) -> 35769.061 | AJ6: =IF($A6="", "", $AI6 * Premissas!$B$12) -> 2861.5249 | AK6: =IF($A6="", "", $AI6 - $AJ6 - $K6 - $L6 - $O6 - $R6 - $T6 - $U6 - SUM($V6:$AE6) - AM6) -> 19955.876 | AL6: =AL5+AK6 -> 53496.625 | AM6: =IF($A6="", "", $B6 * 'Taxas de pagamento'!$B$12 + $AI6 * 'Taxas de pagamento'!$C$13) -> 364.20783
A7: Feb/2027 | B7: =B6+D7 -> 65 | C7: =ROUND(B6*Premissas!$B$2, 0) -> 1 | D7: 20 | E7: =D7+C7 -> 21 | F7: =B7*Premissas!$B$3 -> 21580 | G7: {=IF(DATE(RIGHT(A7, 4), MATCH(LEFT(A7, 3), {"Jan","Feb","Mar","Apr","May","Jun","Jul","Aug","Sep","Oct","Nov","Dec"}, 0), 1) >= Aluguel!$G$2, B7 * Aluguel!$B$2 * Aluguel!$E$2, 0)} -> 3900 | H7: {=SUMPRODUCT('Pacotes adicionais'!$C$2:$C$5, 'Pacotes adicionais'!$D$2:$D$5, --(DATE(RIGHT(A7, 4), MATCH(LEFT(A7, 3), {"Jan","Feb","Mar","Apr","May","Jun","Jul","Aug","Sep","Oct","Nov","Dec"}, 0), 1) >= 'Pacotes adicionais'!$F$2:$F$5)) * B7} -> 614.1525 | I7: =F7 + G7 + H7 -> 26094.153 | J7: =I7-K7-L7 -> 18366.269 | K7: =IF($A7="", "", IFERROR($E7 * ($I7/$B7) * Premissas!$B$6, 0)) -> 4215.2092 | L7: =IF($A7="", "", IFERROR(($E7 * Premissas!$B$4 * ($I7/$B7) + $E6 * Premissas!$B$5 * ($I6/$B6)) * Premissas!$B$7, 0)) -> 3512.6744 | M7: =E7*'Aquisição'!$B$2 -> 12.6 | N7: 200 | O7: =M7*N7 -> 2520 | P7: =E7*'Aquisição'!$B$3 -> 5.25 | Q7: =P7/Premissas!$B$9 -> 262.5 | R7: =Q7*Premissas!$B$8 -> 131.25 | S7: =E7*'Aquisição'!$B$4 -> 3.15 | T7: =S7*Premissas!$B$3*Premissas!$B$13 -> 836.64 | U7: =SUM($S$2:$S7)*(1-Premissas!$B$2)^(ROW()-2)*Premissas!$B$3*Premissas!$B$10 -> 290.80169 | V7: =IF($B7>='Equipe e Remuneração'!$D$6, 'Equipe e Remuneração'!$C$6, 0) -> 2500 | W7: =IF($B7>='Equipe e Remuneração'!$D$3, 'Equipe e Remuneração'!$C$3, 0) -> 2000 | X7: =IF($B7>='Equipe e Remuneração'!$D$5, 'Equipe e Remuneração'!$C$5, 0) -> 0 | Y7: =IF($B7>='Equipe e Remuneração'!$D$7, 'Equipe e Remuneração'!$C$7, 0) -> 0 | Z7: =IF($B7>='Equipe e Remuneração'!$D$9+120, 'Equipe e Remuneração'!$C$9*3, IF($B7>='Equipe e Remuneração'!$D$9+60, 'Equipe e Remuneração'!$C$9*2, IF($B7>='Equipe e Remuneração'!$D$9, 'Equipe e Remuneração'!$C$9, 0))) -> 0 | AA7: =IF($B7>='Equipe e Remuneração'!$D$10+120, 'Equipe e Remuneração'!$C$10+2000, IF($B7>='Equipe e Remuneração'!$D$10+60, 'Equipe e Remuneração'!$C$10+1000, IF($B7>='Equipe e Remuneração'!$D$10, 'Equipe e Remuneração'!$C$10, 0))) -> 0 | AB7: =IF($B7>='Equipe e Remuneração'!$D$8*2, 'Equipe e Remuneração'!$C$8*2, IF($B7>='Equipe e Remuneração'!$D$8, 'Equipe e Remuneração'!$C$8, 0)) -> 0 | AC7: =IF($B7>=280, 2500, IF($B7>=160, 1500, 0)) -> 0 | AD7: =IF($B7>=190, 1500, IF($B7>=110, 1000, IF($B7>=65, 750, IF($B7>=45, 500, IF($B7>=30, 300, 0))))) -> 750 | AE7: =IF($B7>=251, 1359.24, IF($B7>=151, 1132.7, IF($B7>=30, 906.16, 442.15))) -> 906.16 | AF7: =F7*Premissas!$B$12 -> 1726.4 | AG7: =J7 - O7 - R7 - SUM(T7:AE7) - AM7 -> 7930.6016 | AH7: =AG7-AF7 -> 6204.2016 | AI7: =IF($A7="", "", IFERROR(($I7 * Premissas!$B$5) + ($E7 * ($I7/$B7) * Premissas!$B$4 * 12), 0)) -> 48615.413 | AJ7: =IF($A7="", "", $AI7 * Premissas!$B$12) -> 3889.2331 | AK7: =IF($A7="", "", $AI7 - $AJ7 - $K7 - $L7 - $O7 - $R7 - $T7 - $U7 - SUM($V7:$AE7) - AM7) -> 26562.629 | AL7: =AL6+AK7 -> 80059.255 | AM7: =IF($A7="", "", $B7 * 'Taxas de pagamento'!$B$12 + $AI7 * 'Taxas de pagamento'!$C$13) -> 500.81562
A8: Mar/2027 | B8: =B7+D8 -> 85 | C8: =ROUND(B7*Premissas!$B$2, 0) -> 2 | D8: 20 | E8: =D8+C8 -> 22 | F8: =B8*Premissas!$B$3 -> 28220 | G8: {=IF(DATE(RIGHT(A8, 4), MATCH(LEFT(A8, 3), {"Jan","Feb","Mar","Apr","May","Jun","Jul","Aug","Sep","Oct","Nov","Dec"}, 0), 1) >= Aluguel!$G$2, B8 * Aluguel!$B$2 * Aluguel!$E$2, 0)} -> 5100 | H8: {=SUMPRODUCT('Pacotes adicionais'!$C$2:$C$5, 'Pacotes adicionais'!$D$2:$D$5, --(DATE(RIGHT(A8, 4), MATCH(LEFT(A8, 3), {"Jan","Feb","Mar","Apr","May","Jun","Jul","Aug","Sep","Oct","Nov","Dec"}, 0), 1) >= 'Pacotes adicionais'!$F$2:$F$5)) * B8} -> 803.1225 | I8: =F8 + G8 + H8 -> 34123.122 | J8: =I8-K8-L8 -> 25431.762 | K8: =IF($A8="", "", IFERROR($E8 * ($I8/$B8) * Premissas!$B$6, 0)) -> 4415.9335 | L8: =IF($A8="", "", IFERROR(($E8 * Premissas!$B$4 * ($I8/$B8) + $E7 * Premissas!$B$5 * ($I7/$B7)) * Premissas!$B$7, 0)) -> 4275.4265 | M8: =E8*'Aquisição'!$B$2 -> 13.2 | N8: 200 | O8: =M8*N8 -> 2640 | P8: =E8*'Aquisição'!$B$3 -> 5.5 | Q8: =P8/Premissas!$B$9 -> 275 | R8: =Q8*Premissas!$B$8 -> 137.5 | S8: =E8*'Aquisição'!$B$4 -> 3.3 | T8: =S8*Premissas!$B$3*Premissas!$B$13 -> 876.48 | U8: =SUM($S$2:$S8)*(1-Premissas!$B$2)^(ROW()-2)*Premissas!$B$3*Premissas!$B$10 -> 373.33805 | V8: =IF($B8>='Equipe e Remuneração'!$D$6, 'Equipe e Remuneração'!$C$6, 0) -> 2500 | W8: =IF($B8>='Equipe e Remuneração'!$D$3, 'Equipe e Remuneração'!$C$3, 0) -> 2000 | X8: =IF($B8>='Equipe e Remuneração'!$D$5, 'Equipe e Remuneração'!$C$5, 0) -> 3000 | Y8: =IF($B8>='Equipe e Remuneração'!$D$7, 'Equipe e Remuneração'!$C$7, 0) -> 0 | Z8: =IF($B8>='Equipe e Remuneração'!$D$9+120, 'Equipe e Remuneração'!$C$9*3, IF($B8>='Equipe e Remuneração'!$D$9+60, 'Equipe e Remuneração'!$C$9*2, IF($B8>='Equipe e Remuneração'!$D$9, 'Equipe e Remuneração'!$C$9, 0))) -> 0 | AA8: =IF($B8>='Equipe e Remuneração'!$D$10+120, 'Equipe e Remuneração'!$C$10+2000, IF($B8>='Equipe e Remuneração'!$D$10+60, 'Equipe e Remuneração'!$C$10+1000, IF($B8>='Equipe e Remuneração'!$D$10, 'Equipe e Remuneração'!$C$10, 0))) -> 0 | AB8: =IF($B8>='Equipe e Remuneração'!$D$8*2, 'Equipe e Remuneração'!$C$8*2, IF($B8>='Equipe e Remuneração'!$D$8, 'Equipe e Remuneração'!$C$8, 0)) -> 0 | AC8: =IF($B8>=280, 2500, IF($B8>=160, 1500, 0)) -> 0 | AD8: =IF($B8>=190, 1500, IF($B8>=110, 1000, IF($B8>=65, 750, IF($B8>=45, 500, IF($B8>=30, 300, 0))))) -> 750 | AE8: =IF($B8>=251, 1359.24, IF($B8>=151, 1132.7, IF($B8>=30, 906.16, 442.15))) -> 906.16 | AF8: =F8*Premissas!$B$12 -> 2257.6 | AG8: =J8 - O8 - R8 - SUM(T8:AE8) - AM8 -> 11658.727 | AH8: =AG8-AF8 -> 9401.1265 | AI8: =IF($A8="", "", IFERROR(($I8 * Premissas!$B$5) + ($E8 * ($I8/$B8) * Premissas!$B$4 * 12), 0)) -> 55680.907 | AJ8: =IF($A8="", "", $AI8 * Premissas!$B$12) -> 4454.4726 | AK8: =IF($A8="", "", $AI8 - $AJ8 - $K8 - $L8 - $O8 - $R8 - $T8 - $U8 - SUM($V8:$AE8) - AM8) -> 28762.038 | AL8: =AL7+AK8 -> 108821.29 | AM8: =IF($A8="", "", $B8 * 'Taxas de pagamento'!$B$12 + $AI8 * 'Taxas de pagamento'!$C$13) -> 589.55791
A9: Apr/2027 | B9: =B8+D9 -> 110 | C9: =ROUND(B8*Premissas!$B$2, 0) -> 3 | D9: 25 | E9: =D9+C9 -> 28 | F9: =B9*Premissas!$B$3 -> 36520 | G9: {=IF(DATE(RIGHT(A9, 4), MATCH(LEFT(A9, 3), {"Jan","Feb","Mar","Apr","May","Jun","Jul","Aug","Sep","Oct","Nov","Dec"}, 0), 1) >= Aluguel!$G$2, B9 * Aluguel!$B$2 * Aluguel!$E$2, 0)} -> 6600 | H9: {=SUMPRODUCT('Pacotes adicionais'!$C$2:$C$5, 'Pacotes adicionais'!$D$2:$D$5, --(DATE(RIGHT(A9, 4), MATCH(LEFT(A9, 3), {"Jan","Feb","Mar","Apr","May","Jun","Jul","Aug","Sep","Oct","Nov","Dec"}, 0), 1) >= 'Pacotes adicionais'!$F$2:$F$5)) * B9} -> 1039.335 | I9: =F9 + G9 + H9 -> 44159.335 | J9: =I9-K9-L9 -> 33761.819 | K9: =IF($A9="", "", IFERROR($E9 * ($I9/$B9) * Premissas!$B$6, 0)) -> 5620.279 | L9: =IF($A9="", "", IFERROR(($E9 * Premissas!$B$4 * ($I9/$B9) + $E8 * Premissas!$B$5 * ($I8/$B8)) * Premissas!$B$7, 0)) -> 4777.2371 | M9: =E9*'Aquisição'!$B$2 -> 16.8 | N9: 190 | O9: =M9*N9 -> 3192 | P9: =E9*'Aquisição'!$B$3 -> 7 | Q9: =P9/Premissas!$B$9 -> 350 | R9: =Q9*Premissas!$B$8 -> 175 | S9: =E9*'Aquisição'!$B$4 -> 4.2 | T9: =S9*Premissas!$B$3*Premissas!$B$13 -> 1115.52 | U9: =SUM($S$2:$S9)*(1-Premissas!$B$2)^(ROW()-2)*Premissas!$B$3*Premissas!$B$10 -> 474.80304 | V9: =IF($B9>='Equipe e Remuneração'!$D$6, 'Equipe e Remuneração'!$C$6, 0) -> 2500 | W9: =IF($B9>='Equipe e Remuneração'!$D$3, 'Equipe e Remuneração'!$C$3, 0) -> 2000 | X9: =IF($B9>='Equipe e Remuneração'!$D$5, 'Equipe e Remuneração'!$C$5, 0) -> 3000 | Y9: =IF($B9>='Equipe e Remuneração'!$D$7, 'Equipe e Remuneração'!$C$7, 0) -> 1500 | Z9: =IF($B9>='Equipe e Remuneração'!$D$9+120, 'Equipe e Remuneração'!$C$9*3, IF($B9>='Equipe e Remuneração'!$D$9+60, 'Equipe e Remuneração'!$C$9*2, IF($B9>='Equipe e Remuneração'!$D$9, 'Equipe e Remuneração'!$C$9, 0))) -> 0 | AA9: =IF($B9>='Equipe e Remuneração'!$D$10+120, 'Equipe e Remuneração'!$C$10+2000, IF($B9>='Equipe e Remuneração'!$D$10+60, 'Equipe e Remuneração'!$C$10+1000, IF($B9>='Equipe e Remuneração'!$D$10, 'Equipe e Remuneração'!$C$10, 0))) -> 0 | AB9: =IF($B9>='Equipe e Remuneração'!$D$8*2, 'Equipe e Remuneração'!$C$8*2, IF($B9>='Equipe e Remuneração'!$D$8, 'Equipe e Remuneração'!$C$8, 0)) -> 1000 | AC9: =IF($B9>=280, 2500, IF($B9>=160, 1500, 0)) -> 0 | AD9: =IF($B9>=190, 1500, IF($B9>=110, 1000, IF($B9>=65, 750, IF($B9>=45, 500, IF($B9>=30, 300, 0))))) -> 1000 | AE9: =IF($B9>=251, 1359.24, IF($B9>=151, 1132.7, IF($B9>=30, 906.16, 442.15))) -> 906.16 | AF9: =F9*Premissas!$B$12 -> 2921.6 | AG9: =J9 - O9 - R9 - SUM(T9:AE9) - AM9 -> 16141.01 | AH9: =AG9-AF9 -> 13219.41 | AI9: =IF($A9="", "", IFERROR(($I9 * Premissas!$B$5) + ($E9 * ($I9/$B9) * Premissas!$B$4 * 12), 0)) -> 71377.543 | AJ9: =IF($A9="", "", $AI9 * Premissas!$B$12) -> 5710.2035 | AK9: =IF($A9="", "", $AI9 - $AJ9 - $K9 - $L9 - $O9 - $R9 - $T9 - $U9 - SUM($V9:$AE9) - AM9) -> 37649.015 | AL9: =AL8+AK9 -> 146470.31 | AM9: =IF($A9="", "", $B9 * 'Taxas de pagamento'!$B$12 + $AI9 * 'Taxas de pagamento'!$C$13) -> 757.32606
A10: May/2027 | B10: =B9+D10 -> 135 | C10: =ROUND(B9*Premissas!$B$2, 0) -> 3 | D10: 25 | E10: =D10+C10 -> 28 | F10: =B10*Premissas!$B$3 -> 44820 | G10: {=IF(DATE(RIGHT(A10, 4), MATCH(LEFT(A10, 3), {"Jan","Feb","Mar","Apr","May","Jun","Jul","Aug","Sep","Oct","Nov","Dec"}, 0), 1) >= Aluguel!$G$2, B10 * Aluguel!$B$2 * Aluguel!$E$2, 0)} -> 8100 | H10: {=SUMPRODUCT('Pacotes adicionais'!$C$2:$C$5, 'Pacotes adicionais'!$D$2:$D$5, --(DATE(RIGHT(A10, 4), MATCH(LEFT(A10, 3), {"Jan","Feb","Mar","Apr","May","Jun","Jul","Aug","Sep","Oct","Nov","Dec"}, 0), 1) >= 'Pacotes adicionais'!$F$2:$F$5)) * B10} -> 1275.5475 | I10: =F10 + G10 + H10 -> 54195.548 | J10: =I10-K10-L10 -> 42954.99 | K10: =IF($A10="", "", IFERROR($E10 * ($I10/$B10) * Premissas!$B$6, 0)) -> 5620.279 | L10: =IF($A10="", "", IFERROR(($E10 * Premissas!$B$4 * ($I10/$B10) + $E9 * Premissas!$B$5 * ($I9/$B9)) * Premissas!$B$7, 0)) -> 5620.279 | M10: =E10*'Aquisição'!$B$2 -> 16.8 | N10: 190 | O10: =M10*N10 -> 3192 | P10: =E10*'Aquisição'!$B$3 -> 7 | Q10: =P10/Premissas!$B$9 -> 350 | R10: =Q10*Premissas!$B$8 -> 175 | S10: =E10*'Aquisição'!$B$4 -> 4.2 | T10: =S10*Premissas!$B$3*Premissas!$B$13 -> 1115.52 | U10: =SUM($S$2:$S10)*(1-Premissas!$B$2)^(ROW()-2)*Premissas!$B$3*Premissas!$B$10 -> 569.84412 | V10: =IF($B10>='Equipe e Remuneração'!$D$6, 'Equipe e Remuneração'!$C$6, 0) -> 2500 | W10: =IF($B10>='Equipe e Remuneração'!$D$3, 'Equipe e Remuneração'!$C$3, 0) -> 2000 | X10: =IF($B10>='Equipe e Remuneração'!$D$5, 'Equipe e Remuneração'!$C$5, 0) -> 3000 | Y10: =IF($B10>='Equipe e Remuneração'!$D$7, 'Equipe e Remuneração'!$C$7, 0) -> 1500 | Z10: =IF($B10>='Equipe e Remuneração'!$D$9+120, 'Equipe e Remuneração'!$C$9*3, IF($B10>='Equipe e Remuneração'!$D$9+60, 'Equipe e Remuneração'!$C$9*2, IF($B10>='Equipe e Remuneração'!$D$9, 'Equipe e Remuneração'!$C$9, 0))) -> 0 | AA10: =IF($B10>='Equipe e Remuneração'!$D$10+120, 'Equipe e Remuneração'!$C$10+2000, IF($B10>='Equipe e Remuneração'!$D$10+60, 'Equipe e Remuneração'!$C$10+1000, IF($B10>='Equipe e Remuneração'!$D$10, 'Equipe e Remuneração'!$C$10, 0))) -> 0 | AB10: =IF($B10>='Equipe e Remuneração'!$D$8*2, 'Equipe e Remuneração'!$C$8*2, IF($B10>='Equipe e Remuneração'!$D$8, 'Equipe e Remuneração'!$C$8, 0)) -> 1000 | AC10: =IF($B10>=280, 2500, IF($B10>=160, 1500, 0)) -> 0 | AD10: =IF($B10>=190, 1500, IF($B10>=110, 1000, IF($B10>=65, 750, IF($B10>=45, 500, IF($B10>=30, 300, 0))))) -> 1000 | AE10: =IF($B10>=251, 1359.24, IF($B10>=151, 1132.7, IF($B10>=30, 906.16, 442.15))) -> 906.16 | AF10: =F10*Premissas!$B$12 -> 3585.6 | AG10: =J10 - O10 - R10 - SUM(T10:AE10) - AM10 -> 25143.169 | AH10: =AG10-AF10 -> 21557.569 | AI10: =IF($A10="", "", IFERROR(($I10 * Premissas!$B$5) + ($E10 * ($I10/$B10) * Premissas!$B$4 * 12), 0)) -> 78402.892 | AJ10: =IF($A10="", "", $AI10 * Premissas!$B$12) -> 6272.2314 | AK10: =IF($A10="", "", $AI10 - $AJ10 - $K10 - $L10 - $O10 - $R10 - $T10 - $U10 - SUM($V10:$AE10) - AM10) -> 43078.283 | AL10: =AL9+AK10 -> 189548.59 | AM10: =IF($A10="", "", $B10 * 'Taxas de pagamento'!$B$12 + $AI10 * 'Taxas de pagamento'!$C$13) -> 853.29595
A11: Jun/2027 | B11: =B10+D11 -> 160 | C11: =ROUND(B10*Premissas!$B$2, 0) -> 4 | D11: 25 | E11: =D11+C11 -> 29 | F11: =B11*Premissas!$B$3 -> 53120 | G11: {=IF(DATE(RIGHT(A11, 4), MATCH(LEFT(A11, 3), {"Jan","Feb","Mar","Apr","May","Jun","Jul","Aug","Sep","Oct","Nov","Dec"}, 0), 1) >= Aluguel!$G$2, B11 * Aluguel!$B$2 * Aluguel!$E$2, 0)} -> 9600 | H11: {=SUMPRODUCT('Pacotes adicionais'!$C$2:$C$5, 'Pacotes adicionais'!$D$2:$D$5, --(DATE(RIGHT(A11, 4), MATCH(LEFT(A11, 3), {"Jan","Feb","Mar","Apr","May","Jun","Jul","Aug","Sep","Oct","Nov","Dec"}, 0), 1) >= 'Pacotes adicionais'!$F$2:$F$5)) * B11} -> 1511.76 | I11: =F11 + G11 + H11 -> 64231.76 | J11: =I11-K11-L11 -> 52730.26 | K11: =IF($A11="", "", IFERROR($E11 * ($I11/$B11) * Premissas!$B$6, 0)) -> 5821.0032 | L11: =IF($A11="", "", IFERROR(($E11 * Premissas!$B$4 * ($I11/$B11) + $E10 * Premissas!$B$5 * ($I10/$B10)) * Premissas!$B$7, 0)) -> 5680.4963 | M11: =E11*'Aquisição'!$B$2 -> 17.4 | N11: 180 | O11: =M11*N11 -> 3132 | P11: =E11*'Aquisição'!$B$3 -> 7.25 | Q11: =P11/Premissas!$B$9 -> 362.5 | R11: =Q11*Premissas!$B$8 -> 181.25 | S11: =E11*'Aquisição'!$B$4 -> 4.35 | T11: =S11*Premissas!$B$3*Premissas!$B$13 -> 1155.36 | U11: =SUM($S$2:$S11)*(1-Premissas!$B$2)^(ROW()-2)*Premissas!$B$3*Premissas!$B$10 -> 662.54137 | V11: =IF($B11>='Equipe e Remuneração'!$D$6, 'Equipe e Remuneração'!$C$6, 0) -> 2500 | W11: =IF($B11>='Equipe e Remuneração'!$D$3, 'Equipe e Remuneração'!$C$3, 0) -> 2000 | X11: =IF($B11>='Equipe e Remuneração'!$D$5, 'Equipe e Remuneração'!$C$5, 0) -> 3000 | Y11: =IF($B11>='Equipe e Remuneração'!$D$7, 'Equipe e Remuneração'!$C$7, 0) -> 1500 | Z11: =IF($B11>='Equipe e Remuneração'!$D$9+120, 'Equipe e Remuneração'!$C$9*3, IF($B11>='Equipe e Remuneração'!$D$9+60, 'Equipe e Remuneração'!$C$9*2, IF($B11>='Equipe e Remuneração'!$D$9, 'Equipe e Remuneração'!$C$9, 0))) -> 2610 | AA11: =IF($B11>='Equipe e Remuneração'!$D$10+120, 'Equipe e Remuneração'!$C$10+2000, IF($B11>='Equipe e Remuneração'!$D$10+60, 'Equipe e Remuneração'!$C$10+1000, IF($B11>='Equipe e Remuneração'!$D$10, 'Equipe e Remuneração'!$C$10, 0))) -> 1500 | AB11: =IF($B11>='Equipe e Remuneração'!$D$8*2, 'Equipe e Remuneração'!$C$8*2, IF($B11>='Equipe e Remuneração'!$D$8, 'Equipe e Remuneração'!$C$8, 0)) -> 1000 | AC11: =IF($B11>=280, 2500, IF($B11>=160, 1500, 0)) -> 1500 | AD11: =IF($B11>=190, 1500, IF($B11>=110, 1000, IF($B11>=65, 750, IF($B11>=45, 500, IF($B11>=30, 300, 0))))) -> 1000 | AE11: =IF($B11>=251, 1359.24, IF($B11>=151, 1132.7, IF($B11>=30, 906.16, 442.15))) -> 1132.7 | AF11: =F11*Premissas!$B$12 -> 4249.6 | AG11: =J11 - O11 - R11 - SUM(T11:AE11) - AM11 -> 28895.177 | AH11: =AG11-AF11 -> 24645.577 | AI11: =IF($A11="", "", IFERROR(($I11 * Premissas!$B$5) + ($E11 * ($I11/$B11) * Premissas!$B$4 * 12), 0)) -> 86873.455 | AJ11: =IF($A11="", "", $AI11 * Premissas!$B$12) -> 6949.8764 | AK11: =IF($A11="", "", $AI11 - $AJ11 - $K11 - $L11 - $O11 - $R11 - $T11 - $U11 - SUM($V11:$AE11) - AM11) -> 44586.996 | AL11: =AL10+AK11 -> 234135.59 | AM11: =IF($A11="", "", $B11 * 'Taxas de pagamento'!$B$12 + $AI11 * 'Taxas de pagamento'!$C$13) -> 961.23221
A12: Jul/2027 | B12: =B11+D12 -> 190 | C12: =ROUND(B11*Premissas!$B$2, 0) -> 5 | D12: 30 | E12: =D12+C12 -> 35 | F12: =B12*Premissas!$B$3 -> 63080 | G12: {=IF(DATE(RIGHT(A12, 4), MATCH(LEFT(A12, 3), {"Jan","Feb","Mar","Apr","May","Jun","Jul","Aug","Sep","Oct","Nov","Dec"}, 0), 1) >= Aluguel!$G$2, B12 * Aluguel!$B$2 * Aluguel!$E$2, 0)} -> 11400 | H12: {=SUMPRODUCT('Pacotes adicionais'!$C$2:$C$5, 'Pacotes adicionais'!$D$2:$D$5, --(DATE(RIGHT(A12, 4), MATCH(LEFT(A12, 3), {"Jan","Feb","Mar","Apr","May","Jun","Jul","Aug","Sep","Oct","Nov","Dec"}, 0), 1) >= 'Pacotes adicionais'!$F$2:$F$5)) * B12} -> 1795.215 | I12: =F12 + G12 + H12 -> 76275.215 | J12: =I12-K12-L12 -> 63067.559 | K12: =IF($A12="", "", IFERROR($E12 * ($I12/$B12) * Premissas!$B$6, 0)) -> 7025.3488 | L12: =IF($A12="", "", IFERROR(($E12 * Premissas!$B$4 * ($I12/$B12) + $E11 * Premissas!$B$5 * ($I11/$B11)) * Premissas!$B$7, 0)) -> 6182.3069 | M12: =E12*'Aquisição'!$B$2 -> 21 | N12: 180 | O12: =M12*N12 -> 3780 | P12: =E12*'Aquisição'!$B$3 -> 8.75 | Q12: =P12/Premissas!$B$9 -> 437.5 | R12: =Q12*Premissas!$B$8 -> 218.75 | S12: =E12*'Aquisição'!$B$4 -> 5.25 | T12: =S12*Premissas!$B$3*Premissas!$B$13 -> 1394.4 | U12: =SUM($S$2:$S12)*(1-Premissas!$B$2)^(ROW()-2)*Premissas!$B$3*Premissas!$B$10 -> 771.19815 | V12: =IF($B12>='Equipe e Remuneração'!$D$6, 'Equipe e Remuneração'!$C$6, 0) -> 2500 | W12: =IF($B12>='Equipe e Remuneração'!$D$3, 'Equipe e Remuneração'!$C$3, 0) -> 2000 | X12: =IF($B12>='Equipe e Remuneração'!$D$5, 'Equipe e Remuneração'!$C$5, 0) -> 3000 | Y12: =IF($B12>='Equipe e Remuneração'!$D$7, 'Equipe e Remuneração'!$C$7, 0) -> 1500 | Z12: =IF($B12>='Equipe e Remuneração'!$D$9+120, 'Equipe e Remuneração'!$C$9*3, IF($B12>='Equipe e Remuneração'!$D$9+60, 'Equipe e Remuneração'!$C$9*2, IF($B12>='Equipe e Remuneração'!$D$9, 'Equipe e Remuneração'!$C$9, 0))) -> 2610 | AA12: =IF($B12>='Equipe e Remuneração'!$D$10+120, 'Equipe e Remuneração'!$C$10+2000, IF($B12>='Equipe e Remuneração'!$D$10+60, 'Equipe e Remuneração'!$C$10+1000, IF($B12>='Equipe e Remuneração'!$D$10, 'Equipe e Remuneração'!$C$10, 0))) -> 1500 | AB12: =IF($B12>='Equipe e Remuneração'!$D$8*2, 'Equipe e Remuneração'!$C$8*2, IF($B12>='Equipe e Remuneração'!$D$8, 'Equipe e Remuneração'!$C$8, 0)) -> 1000 | AC12: =IF($B12>=280, 2500, IF($B12>=160, 1500, 0)) -> 1500 | AD12: =IF($B12>=190, 1500, IF($B12>=110, 1000, IF($B12>=65, 750, IF($B12>=45, 500, IF($B12>=30, 300, 0))))) -> 1500 | AE12: =IF($B12>=251, 1359.24, IF($B12>=151, 1132.7, IF($B12>=30, 906.16, 442.15))) -> 1132.7 | AF12: =F12*Premissas!$B$12 -> 5046.4 | AG12: =J12 - O12 - R12 - SUM(T12:AE12) - AM12 -> 37512.317 | AH12: =AG12-AF12 -> 32465.917 | AI12: =IF($A12="", "", IFERROR(($I12 * Premissas!$B$5) + ($E12 * ($I12/$B12) * Premissas!$B$4 * 12), 0)) -> 103975.16 | AJ12: =IF($A12="", "", $AI12 * Premissas!$B$12) -> 8318.0129 | AK12: =IF($A12="", "", $AI12 - $AJ12 - $K12 - $L12 - $O12 - $R12 - $T12 - $U12 - SUM($V12:$AE12) - AM12) -> 56894.25 | AL12: =AL11+AK12 -> 291029.84 | AM12: =IF($A12="", "", $B12 * 'Taxas de pagamento'!$B$12 + $AI12 * 'Taxas de pagamento'!$C$13) -> 1148.1943
A13: Aug/2027 | B13: =B12+D13 -> 220 | C13: =ROUND(B12*Premissas!$B$2, 0) -> 6 | D13: 30 | E13: =D13+C13 -> 36 | F13: =B13*Premissas!$B$3 -> 73040 | G13: {=IF(DATE(RIGHT(A13, 4), MATCH(LEFT(A13, 3), {"Jan","Feb","Mar","Apr","May","Jun","Jul","Aug","Sep","Oct","Nov","Dec"}, 0), 1) >= Aluguel!$G$2, B13 * Aluguel!$B$2 * Aluguel!$E$2, 0)} -> 13200 | H13: {=SUMPRODUCT('Pacotes adicionais'!$C$2:$C$5, 'Pacotes adicionais'!$D$2:$D$5, --(DATE(RIGHT(A13, 4), MATCH(LEFT(A13, 3), {"Jan","Feb","Mar","Apr","May","Jun","Jul","Aug","Sep","Oct","Nov","Dec"}, 0), 1) >= 'Pacotes adicionais'!$F$2:$F$5)) * B13} -> 2078.67 | I13: =F13 + G13 + H13 -> 88318.67 | J13: =I13-K13-L13 -> 74007.031 | K13: =IF($A13="", "", IFERROR($E13 * ($I13/$B13) * Premissas!$B$6, 0)) -> 7226.073 | L13: =IF($A13="", "", IFERROR(($E13 * Premissas!$B$4 * ($I13/$B13) + $E12 * Premissas!$B$5 * ($I12/$B12)) * Premissas!$B$7, 0)) -> 7085.566 | M13: =E13*'Aquisição'!$B$2 -> 21.6 | N13: 170 | O13: =M13*N13 -> 3672 | P13: =E13*'Aquisição'!$B$3 -> 9 | Q13: =P13/Premissas!$B$9 -> 450 | R13: =Q13*Premissas!$B$8 -> 225 | S13: =E13*'Aquisição'!$B$4 -> 5.4 | T13: =S13*Premissas!$B$3*Premissas!$B$13 -> 1434.24 | U13: =SUM($S$2:$S13)*(1-Premissas!$B$2)^(ROW()-2)*Premissas!$B$3*Premissas!$B$10 -> 876.30144 | V13: =IF($B13>='Equipe e Remuneração'!$D$6, 'Equipe e Remuneração'!$C$6, 0) -> 2500 | W13: =IF($B13>='Equipe e Remuneração'!$D$3, 'Equipe e Remuneração'!$C$3, 0) -> 2000 | X13: =IF($B13>='Equipe e Remuneração'!$D$5, 'Equipe e Remuneração'!$C$5, 0) -> 3000 | Y13: =IF($B13>='Equipe e Remuneração'!$D$7, 'Equipe e Remuneração'!$C$7, 0) -> 1500 | Z13: =IF($B13>='Equipe e Remuneração'!$D$9+120, 'Equipe e Remuneração'!$C$9*3, IF($B13>='Equipe e Remuneração'!$D$9+60, 'Equipe e Remuneração'!$C$9*2, IF($B13>='Equipe e Remuneração'!$D$9, 'Equipe e Remuneração'!$C$9, 0))) -> 5220 | AA13: =IF($B13>='Equipe e Remuneração'!$D$10+120, 'Equipe e Remuneração'!$C$10+2000, IF($B13>='Equipe e Remuneração'!$D$10+60, 'Equipe e Remuneração'!$C$10+1000, IF($B13>='Equipe e Remuneração'!$D$10, 'Equipe e Remuneração'!$C$10, 0))) -> 2500 | AB13: =IF($B13>='Equipe e Remuneração'!$D$8*2, 'Equipe e Remuneração'!$C$8*2, IF($B13>='Equipe e Remuneração'!$D$8, 'Equipe e Remuneração'!$C$8, 0)) -> 2000 | AC13: =IF($B13>=280, 2500, IF($B13>=160, 1500, 0)) -> 1500 | AD13: =IF($B13>=190, 1500, IF($B13>=110, 1000, IF($B13>=65, 750, IF($B13>=45, 500, IF($B13>=30, 300, 0))))) -> 1500 | AE13: =IF($B13>=251, 1359.24, IF($B13>=151, 1132.7, IF($B13>=30, 906.16, 442.15))) -> 1132.7 | AF13: =F13*Premissas!$B$12 -> 5843.2 | AG13: =J13 - O13 - R13 - SUM(T13:AE13) - AM13 -> 43671.465 | AH13: =AG13-AF13 -> 37828.265 | AI13: =IF($A13="", "", IFERROR(($I13 * Premissas!$B$5) + ($E13 * ($I13/$B13) * Premissas!$B$4 * 12), 0)) -> 113850.79 | AJ13: =IF($A13="", "", $AI13 * Premissas!$B$12) -> 9108.0636 | AK13: =IF($A13="", "", $AI13 - $AJ13 - $K13 - $L13 - $O13 - $R13 - $T13 - $U13 - SUM($V13:$AE13) - AM13) -> 60095.526 | AL13: =AL12+AK13 -> 351125.36 | AM13: =IF($A13="", "", $B13 * 'Taxas de pagamento'!$B$12 + $AI13 * 'Taxas de pagamento'!$C$13) -> 1275.3246
A14: Sep/2027 | B14: =B13+D14 -> 250 | C14: =ROUND(B13*Premissas!$B$2, 0) -> 7 | D14: 30 | E14: =D14+C14 -> 37 | F14: =B14*Premissas!$B$3 -> 83000 | G14: {=IF(DATE(RIGHT(A14, 4), MATCH(LEFT(A14, 3), {"Jan","Feb","Mar","Apr","May","Jun","Jul","Aug","Sep","Oct","Nov","Dec"}, 0), 1) >= Aluguel!$G$2, B14 * Aluguel!$B$2 * Aluguel!$E$2, 0)} -> 15000 | H14: {=SUMPRODUCT('Pacotes adicionais'!$C$2:$C$5, 'Pacotes adicionais'!$D$2:$D$5, --(DATE(RIGHT(A14, 4), MATCH(LEFT(A14, 3), {"Jan","Feb","Mar","Apr","May","Jun","Jul","Aug","Sep","Oct","Nov","Dec"}, 0), 1) >= 'Pacotes adicionais'!$F$2:$F$5)) * B14} -> 2362.125 | I14: =F14 + G14 + H14 -> 100362.12 | J14: =I14-K14-L14 -> 85649.037 | K14: =IF($A14="", "", IFERROR($E14 * ($I14/$B14) * Premissas!$B$6, 0)) -> 7426.7972 | L14: =IF($A14="", "", IFERROR(($E14 * Premissas!$B$4 * ($I14/$B14) + $E13 * Premissas!$B$5 * ($I13/$B13)) * Premissas!$B$7, 0)) -> 7286.2903 | M14: =E14*'Aquisição'!$B$2 -> 22.2 | N14: 170 | O14: =M14*N14 -> 3774 | P14: =E14*'Aquisição'!$B$3 -> 9.25 | Q14: =P14/Premissas!$B$9 -> 462.5 | R14: =Q14*Premissas!$B$8 -> 231.25 | S14: =E14*'Aquisição'!$B$4 -> 5.55 | T14: =S14*Premissas!$B$3*Premissas!$B$13 -> 1474.08 | U14: =SUM($S$2:$S14)*(1-Premissas!$B$2)^(ROW()-2)*Premissas!$B$3*Premissas!$B$10 -> 977.85979 | V14: =IF($B14>='Equipe e Remuneração'!$D$6, 'Equipe e Remuneração'!$C$6, 0) -> 2500 | W14: =IF($B14>='Equipe e Remuneração'!$D$3, 'Equipe e Remuneração'!$C$3, 0) -> 2000 | X14: =IF($B14>='Equipe e Remuneração'!$D$5, 'Equipe e Remuneração'!$C$5, 0) -> 3000 | Y14: =IF($B14>='Equipe e Remuneração'!$D$7, 'Equipe e Remuneração'!$C$7, 0) -> 1500 | Z14: =IF($B14>='Equipe e Remuneração'!$D$9+120, 'Equipe e Remuneração'!$C$9*3, IF($B14>='Equipe e Remuneração'!$D$9+60, 'Equipe e Remuneração'!$C$9*2, IF($B14>='Equipe e Remuneração'!$D$9, 'Equipe e Remuneração'!$C$9, 0))) -> 5220 | AA14: =IF($B14>='Equipe e Remuneração'!$D$10+120, 'Equipe e Remuneração'!$C$10+2000, IF($B14>='Equipe e Remuneração'!$D$10+60, 'Equipe e Remuneração'!$C$10+1000, IF($B14>='Equipe e Remuneração'!$D$10, 'Equipe e Remuneração'!$C$10, 0))) -> 2500 | AB14: =IF($B14>='Equipe e Remuneração'!$D$8*2, 'Equipe e Remuneração'!$C$8*2, IF($B14>='Equipe e Remuneração'!$D$8, 'Equipe e Remuneração'!$C$8, 0)) -> 2000 | AC14: =IF($B14>=280, 2500, IF($B14>=160, 1500, 0)) -> 1500 | AD14: =IF($B14>=190, 1500, IF($B14>=110, 1000, IF($B14>=65, 750, IF($B14>=45, 500, IF($B14>=30, 300, 0))))) -> 1500 | AE14: =IF($B14>=251, 1359.24, IF($B14>=151, 1132.7, IF($B14>=30, 906.16, 442.15))) -> 1132.7 | AF14: =F14*Premissas!$B$12 -> 6640 | AG14: =J14 - O14 - R14 - SUM(T14:AE14) - AM14 -> 54936.693 | AH14: =AG14-AF14 -> 48296.693 | AI14: =IF($A14="", "", IFERROR(($I14 * Premissas!$B$5) + ($E14 * ($I14/$B14) * Premissas!$B$4 * 12), 0)) -> 123726.43 | AJ14: =IF($A14="", "", $AI14 * Premissas!$B$12) -> 9898.1142 | AK14: =IF($A14="", "", $AI14 - $AJ14 - $K14 - $L14 - $O14 - $R14 - $T14 - $U14 - SUM($V14:$AE14) - AM14) -> 68402.881 | AL14: =AL13+AK14 -> 419528.24 | AM14: =IF($A14="", "", $B14 * 'Taxas de pagamento'!$B$12 + $AI14 * 'Taxas de pagamento'!$C$13) -> 1402.4548
... A17: Dec/2027 | B17: =B16+D17 -> 345 | C17: =ROUND(B16*Premissas!$B$2, 0) -> 9 | D17: 35 | E17: =D17+C17 -> 44 | F17: =B17*Premissas!$B$3 -> 114540 | G17: {=IF(DATE(RIGHT(A17, 4), MATCH(LEFT(A17, 3), {"Jan","Feb","Mar","Apr","May","Jun","Jul","Aug","Sep","Oct","Nov","Dec"}, 0), 1) >= Aluguel!$G$2, B17 * Aluguel!$B$2 * Aluguel!$E$2, 0)} -> 20700 | H17: {=SUMPRODUCT('Pacotes adicionais'!$C$2:$C$5, 'Pacotes adicionais'!$D$2:$D$5, --(DATE(RIGHT(A17, 4), MATCH(LEFT(A17, 3), {"Jan","Feb","Mar","Apr","May","Jun","Jul","Aug","Sep","Oct","Nov","Dec"}, 0), 1) >= 'Pacotes adicionais'!$F$2:$F$5)) * B17} -> 3259.7325 | I17: =F17 + G17 + H17 -> 138499.73 | J17: =I17-K17-L17 -> 121679.04 | K17: =IF($A17="", "", IFERROR($E17 * ($I17/$B17) * Premissas!$B$6, 0)) -> 8831.867 | L17: =IF($A17="", "", IFERROR(($E17 * Premissas!$B$4 * ($I17/$B17) + $E16 * Premissas!$B$5 * ($I16/$B16)) * Premissas!$B$7, 0)) -> 7988.8251 | M17: =E17*'Aquisição'!$B$2 -> 26.4 | N17: 160 | O17: =M17*N17 -> 4224 | P17: =E17*'Aquisição'!$B$3 -> 11 | Q17: =P17/Premissas!$B$9 -> 550 | R17: =Q17*Premissas!$B$8 -> 275 | S17: =E17*'Aquisição'!$B$4 -> 6.6 | T17: =S17*Premissas!$B$3*Premissas!$B$13 -> 1752.96 | U17: =SUM($S$2:$S17)*(1-Premissas!$B$2)^(ROW()-2)*Premissas!$B$3*Premissas!$B$10 -> 1270.8971 | V17: =IF($B17>='Equipe e Remuneração'!$D$6, 'Equipe e Remuneração'!$C$6, 0) -> 2500 | W17: =IF($B17>='Equipe e Remuneração'!$D$3, 'Equipe e Remuneração'!$C$3, 0) -> 2000 | X17: =IF($B17>='Equipe e Remuneração'!$D$5, 'Equipe e Remuneração'!$C$5, 0) -> 3000 | Y17: =IF($B17>='Equipe e Remuneração'!$D$7, 'Equipe e Remuneração'!$C$7, 0) -> 1500 | Z17: =IF($B17>='Equipe e Remuneração'!$D$9+120, 'Equipe e Remuneração'!$C$9*3, IF($B17>='Equipe e Remuneração'!$D$9+60, 'Equipe e Remuneração'!$C$9*2, IF($B17>='Equipe e Remuneração'!$D$9, 'Equipe e Remuneração'!$C$9, 0))) -> 7830 | AA17: =IF($B17>='Equipe e Remuneração'!$D$10+120, 'Equipe e Remuneração'!$C$10+2000, IF($B17>='Equipe e Remuneração'!$D$10+60, 'Equipe e Remuneração'!$C$10+1000, IF($B17>='Equipe e Remuneração'!$D$10, 'Equipe e Remuneração'!$C$10, 0))) -> 3500 | AB17: =IF($B17>='Equipe e Remuneração'!$D$8*2, 'Equipe e Remuneração'!$C$8*2, IF($B17>='Equipe e Remuneração'!$D$8, 'Equipe e Remuneração'!$C$8, 0)) -> 2000 | AC17: =IF($B17>=280, 2500, IF($B17>=160, 1500, 0)) -> 2500 | AD17: =IF($B17>=190, 1500, IF($B17>=110, 1000, IF($B17>=65, 750, IF($B17>=45, 500, IF($B17>=30, 300, 0))))) -> 1500 | AE17: =IF($B17>=251, 1359.24, IF($B17>=151, 1132.7, IF($B17>=30, 906.16, 442.15))) -> 1359.24 | AF17: =F17*Premissas!$B$12 -> 9163.2 | AG17: =J17 - O17 - R17 - SUM(T17:AE17) - AM17 -> 84616.038 | AH17: =AG17-AF17 -> 75452.838 | AI17: =IF($A17="", "", IFERROR(($I17 * Premissas!$B$5) + ($E17 * ($I17/$B17) * Premissas!$B$4 * 12), 0)) -> 160539.26 | AJ17: =IF($A17="", "", $AI17 * Premissas!$B$12) -> 12843.14 | AK17: =IF($A17="", "", $AI17 - $AJ17 - $K17 - $L17 - $O17 - $R17 - $T17 - $U17 - SUM($V17:$AE17) - AM17) -> 93812.42 | AL17: =AL16+AK17 -> 664846.17 | AM17: =IF($A17="", "", $B17 * 'Taxas de pagamento'!$B$12 + $AI17 * 'Taxas de pagamento'!$C$13) -> 1850.905
K18: =IF($A18="", "", IFERROR($E18 * ($I18/$B18) * Premissas!$B$6, 0)) | L18: =IF($A18="", "", IFERROR(($E18 * Premissas!$B$4 * ($I18/$B18) + $E17 * Premissas!$B$5 * ($I17/$B17)) * Premissas!$B$7, 0)) | AI18: =IF($A18="", "", IFERROR(($I18 * Premissas!$B$5) + ($E18 * ($I18/$B18) * Premissas!$B$4 * 12), 0)) | AJ18: =IF($A18="", "", $AI18 * Premissas!$B$12) | AK18: =IF($A18="", "", $AI18 - $AJ18 - $K18 - $L18 - $O18 - $R18 - $T18 - $U18 - SUM($V18:$AE18))
K19: =IF($A19="", "", IFERROR($E19 * ($I19/$B19) * Premissas!$B$6, 0)) | L19: =IF($A19="", "", IFERROR(($E19 * Premissas!$B$4 * ($I19/$B19) + $E18 * Premissas!$B$5 * ($I18/$B18)) * Premissas!$B$7, 0)) | AI19: =IF($A19="", "", IFERROR(($I19 * Premissas!$B$5) + ($E19 * ($I19/$B19) * Premissas!$B$4 * 12), 0)) | AJ19: =IF($A19="", "", $AI19 * Premissas!$B$12) | AK19: =IF($A19="", "", $AI19 - $AJ19 - $K19 - $L19 - $O19 - $R19 - $T19 - $U19 - SUM($V19:$AE19))
K20: =IF($A20="", "", IFERROR($E20 * ($I20/$B20) * Premissas!$B$6, 0)) | L20: =IF($A20="", "", IFERROR(($E20 * Premissas!$B$4 * ($I20/$B20) + $E19 * Premissas!$B$5 * ($I19/$B19)) * Premissas!$B$7, 0)) | AI20: =IF($A20="", "", IFERROR(($I20 * Premissas!$B$5) + ($E20 * ($I20/$B20) * Premissas!$B$4 * 12), 0)) | AJ20: =IF($A20="", "", $AI20 * Premissas!$B$12) | AK20: =IF($A20="", "", $AI20 - $AJ20 - $K20 - $L20 - $O20 - $R20 - $T20 - $U20 - SUM($V20:$AE20))
K21: =IF($A21="", "", IFERROR($E21 * ($I21/$B21) * Premissas!$B$6, 0)) | L21: =IF($A21="", "", IFERROR(($E21 * Premissas!$B$4 * ($I21/$B21) + $E20 * Premissas!$B$5 * ($I20/$B20)) * Premissas!$B$7, 0)) | AI21: =IF($A21="", "", IFERROR(($I21 * Premissas!$B$5) + ($E21 * ($I21/$B21) * Premissas!$B$4 * 12), 0)) | AJ21: =IF($A21="", "", $AI21 * Premissas!$B$12) | AK21: =IF($A21="", "", $AI21 - $AJ21 - $K21 - $L21 - $O21 - $R21 - $T21 - $U21 - SUM($V21:$AE21))
K22: =IF($A22="", "", IFERROR($E22 * ($I22/$B22) * Premissas!$B$6, 0)) | L22: =IF($A22="", "", IFERROR(($E22 * Premissas!$B$4 * ($I22/$B22) + $E21 * Premissas!$B$5 * ($I21/$B21)) * Premissas!$B$7, 0)) | AI22: =IF($A22="", "", IFERROR(($I22 * Premissas!$B$5) + ($E22 * ($I22/$B22) * Premissas!$B$4 * 12), 0)) | AJ22: =IF($A22="", "", $AI22 * Premissas!$B$12) | AK22: =IF($A22="", "", $AI22 - $AJ22 - $K22 - $L22 - $O22 - $R22 - $T22 - $U22 - SUM($V22:$AE22))
K23: =IF($A23="", "", IFERROR($E23 * ($I23/$B23) * Premissas!$B$6, 0)) | L23: =IF($A23="", "", IFERROR(($E23 * Premissas!$B$4 * ($I23/$B23) + $E22 * Premissas!$B$5 * ($I22/$B22)) * Premissas!$B$7, 0)) | AI23: =IF($A23="", "", IFERROR(($I23 * Premissas!$B$5) + ($E23 * ($I23/$B23) * Premissas!$B$4 * 12), 0)) | AJ23: =IF($A23="", "", $AI23 * Premissas!$B$12) | AK23: =IF($A23="", "", $AI23 - $AJ23 - $K23 - $L23 - $O23 - $R23 - $T23 - $U23 - SUM($V23:$AE23))
K24: =IF($A24="", "", IFERROR($E24 * ($I24/$B24) * Premissas!$B$6, 0)) | L24: =IF($A24="", "", IFERROR(($E24 * Premissas!$B$4 * ($I24/$B24) + $E23 * Premissas!$B$5 * ($I23/$B23)) * Premissas!$B$7, 0)) | AI24: =IF($A24="", "", IFERROR(($I24 * Premissas!$B$5) + ($E24 * ($I24/$B24) * Premissas!$B$4 * 12), 0)) | AJ24: =IF($A24="", "", $AI24 * Premissas!$B$12) | AK24: =IF($A24="", "", $AI24 - $AJ24 - $K24 - $L24 - $O24 - $R24 - $T24 - $U24 - SUM($V24:$AE24))
K25: =IF($A25="", "", IFERROR($E25 * ($I25/$B25) * Premissas!$B$6, 0)) | L25: =IF($A25="", "", IFERROR(($E25 * Premissas!$B$4 * ($I25/$B25) + $E24 * Premissas!$B$5 * ($I24/$B24)) * Premissas!$B$7, 0)) | AI25: =IF($A25="", "", IFERROR(($I25 * Premissas!$B$5) + ($E25 * ($I25/$B25) * Premissas!$B$4 * 12), 0)) | AJ25: =IF($A25="", "", $AI25 * Premissas!$B$12) | AK25: =IF($A25="", "", $AI25 - $AJ25 - $K25 - $L25 - $O25 - $R25 - $T25 - $U25 - SUM($V25:$AE25))
K26: =IF($A26="", "", IFERROR($E26 * ($I26/$B26) * Premissas!$B$6, 0)) | L26: =IF($A26="", "", IFERROR(($E26 * Premissas!$B$4 * ($I26/$B26) + $E25 * Premissas!$B$5 * ($I25/$B25)) * Premissas!$B$7, 0)) | AI26: =IF($A26="", "", IFERROR(($I26 * Premissas!$B$5) + ($E26 * ($I26/$B26) * Premissas!$B$4 * 12), 0)) | AJ26: =IF($A26="", "", $AI26 * Premissas!$B$12) | AK26: =IF($A26="", "", $AI26 - $AJ26 - $K26 - $L26 - $O26 - $R26 - $T26 - $U26 - SUM($V26:$AE26))
K27: =IF($A27="", "", IFERROR($E27 * ($I27/$B27) * Premissas!$B$6, 0)) | L27: =IF($A27="", "", IFERROR(($E27 * Premissas!$B$4 * ($I27/$B27) + $E26 * Premissas!$B$5 * ($I26/$B26)) * Premissas!$B$7, 0)) | AI27: =IF($A27="", "", IFERROR(($I27 * Premissas!$B$5) + ($E27 * ($I27/$B27) * Premissas!$B$4 * 12), 0)) | AJ27: =IF($A27="", "", $AI27 * Premissas!$B$12) | AK27: =IF($A27="", "", $AI27 - $AJ27 - $K27 - $L27 - $O27 - $R27 - $T27 - $U27 - SUM($V27:$AE27))
K28: =IF($A28="", "", IFERROR($E28 * ($I28/$B28) * Premissas!$B$6, 0)) | L28: =IF($A28="", "", IFERROR(($E28 * Premissas!$B$4 * ($I28/$B28) + $E27 * Premissas!$B$5 * ($I27/$B27)) * Premissas!$B$7, 0)) | AI28: =IF($A28="", "", IFERROR(($I28 * Premissas!$B$5) + ($E28 * ($I28/$B28) * Premissas!$B$4 * 12), 0)) | AJ28: =IF($A28="", "", $AI28 * Premissas!$B$12) | AK28: =IF($A28="", "", $AI28 - $AJ28 - $K28 - $L28 - $O28 - $R28 - $T28 - $U28 - SUM($V28:$AE28))
K29: =IF($A29="", "", IFERROR($E29 * ($I29/$B29) * Premissas!$B$6, 0)) | L29: =IF($A29="", "", IFERROR(($E29 * Premissas!$B$4 * ($I29/$B29) + $E28 * Premissas!$B$5 * ($I28/$B28)) * Premissas!$B$7, 0)) | AI29: =IF($A29="", "", IFERROR(($I29 * Premissas!$B$5) + ($E29 * ($I29/$B29) * Premissas!$B$4 * 12), 0)) | AJ29: =IF($A29="", "", $AI29 * Premissas!$B$12) | AK29: =IF($A29="", "", $AI29 - $AJ29 - $K29 - $L29 - $O29 - $R29 - $T29 - $U29 - SUM($V29:$AE29))
... K1000: =IF($A1000="", "", IFERROR($E1000 * ($I1000/$B1000) * Premissas!$B$6, 0)) | L1000: =IF($A1000="", "", IFERROR(($E1000 * Premissas!$B$4 * ($I1000/$B1000) + $E999 * Premissas!$B$5 * ($I999/$B999)) * Premissas!$B$7, 0)) | AI1000: =IF($A1000="", "", IFERROR(($I1000 * Premissas!$B$5) + ($E1000 * ($I1000/$B1000) * Premissas!$B$4 * 12), 0)) | AJ1000: =IF($A1000="", "", $AI1000 * Premissas!$B$12) | AK1000: =IF($A1000="", "", $AI1000 - $AJ1000 - $K1000 - $L1000 - $O1000 - $R1000 - $T1000 - $U1000 - SUM($V1000:$AE1000))

Sheet Planos
A1: Plano | B1: Mensal | C1: Anual equivalente mensal | D1: Anual à vista | E1: Previsão de vendas %
A2: Grátis | B2: 0 | C2: 0 | D2: 0 | E2: 0
A3: Corretor Pro | B3: 120 | C3: 96 | D3: 1152 | E3: 0.1
A4: Imobiliária Basic | B4: 220 | C4: 176 | D4: 2112 | E4: 0.25
A5: Imobiliária Pro | B5: 350 | C5: 280 | D5: 3360 | E5: 0.5
A6: Imobiliária Master | B6: 600 | C6: 480 | D6: 5760 | E6: 0.15

Sheet Aluguel
A1: Plano | B1: Mensal | C1: Anual equivalente mensal | D1: Anual à vista | E1: Previsão de vendas % | F1: Vendido para a base de clientes | G1: Previsão de lançamento
A2: Módulo de Alugueis | B2: 200 | C2: 160 | D2: 1920 | E2: 0.3 | F2: Sim | G2: 46327

Sheet Pacotes adicionais
A1: Pacotes adicionais | B1: Quantidade adicional | C1: Valor | D1: Previsão de vendas % | E1: Vendido para a base de clientes | F1: Previsão de lançamento
A2: Usuários adicionais | B2: 1 | C2: 29.99 | D2: 0.07 | E2: Sim | F2: 46266
A3: Imóveis adicionais | B3: 100 | C3: 19.99 | D3: 0.08 | E3: Sim | F3: 46266
A4: Email profissional | B4: 1 | C4: 5 | D4: 0.15 | E4: Sim | F4: 46296
A5: Assinatura Digital | B5: 10 | C5: 50 | D5: 0.1 | E5: Sim | F5: 46296

Sheet Equipe e Remuneração
A1: Área | B1: Modelo | C1: Remuneração | D1: Gatilho
A2: Vendas | B2: Parceiros/comissionados | C2: 0.5 | D2: 0
A3: Gestor comercial | B3: Sócio | C3: 2000 | D3: 65
A4: Suporte | B4: Parceiros inicialmente; depois fixo | C4: 0.5 | D4: 0
A5: Marketing/Growth | B5: Sócio | C5: 3000 | D5: 85
A6: Desenvolvimento | B6: Sócio | C6: 2500 | D6: 30
A7: Administrativo/financeiro | B7: Sócio | C7: 1500 | D7: 110
A8: SDR | B8: Freelancer/CLT | C8: 1000 | D8: 110
A9: Suporte fixo | B9: CLT/contrato | C9: 2610 | D9: 160
A10: Apoio técnico | B10: Freelancer/CLT | C10: 1500 | D10: 160

Sheet Infraestrutura
A1: Faixa | B1: Item | C1: Mensal
A2: Até 29 | B2: Contabilidade | C2: 100
A3: Até 29 | B3: Vercel | C3: 104
A4: Até 29 | B4: Neon | C4: 104
A5: Até 29 | B5: Domínio | C5: 4.16
A6: Até 29 | B6: Hostinger | C6: 129.99
A7: Até 29 | B7: TOTAL | C7: 442.15
A8: 30–150 | B8: Contabilidade | C8: 130
A9: 30–150 | B9: Vercel | C9: 104
A10: 30–150 | B10: Neon | C10: 104
A11: 30–150 | B11: Domínio | C11: 4.16
A12: 30–150 | B12: Hostinger | C12: 200
A13: 30–150 | B13: Resend | C13: 104
... A18: 251–345 | B18: Reserva de escala | C18: 1359.24

Sheet Aquisição
A1: Canal | B1: Participação | C1: Regra
A2: Tráfego pago | B2: 60% | C2: CAC variável; premissa inicial R$250→R$160
A3: Listas frias | B3: 25% | C3: R$0,50/contato; conversão assumida 2%
A4: Microinfluenciadores | B4: 15% | C4: 1ª parcela + 10% recorrência; 30% OFF 1º mês

Sheet Premissas
A1: Premissa | B1: Valor
A2: Churn mensal | B2: 0.03
A3: Ticket usado na meta | B3: =SUMPRODUCT(Planos!B2:B6, Planos!E2:E6) -> 332
A4: Clientes anuais | B4: 0.3
A5: Clientes mensais | B5: 0.7
A6: Comissão vendas | B6: 0.5
A7: Comissão suporte | B7: 0.5
A8: Lista fria R$/contato | B8: 0.5
A9: Conversão lista fria | B9: 0.02
A10: Influencer % recorrência | B10: 0.1
A11: Influencer desconto 1º mês | B11: 0.2
A12: Impostos | B12: 0.08
A13: Comissão influencer (1º parcela) | B13: 0.8

Sheet Taxas de pagamento
A1: Método de Pagamento | B1: Taxa Fixa (R$) | C1: Taxa Variável (%) | D1: Uso Estimado (%)
A2: Pix | B2: 1.99 | C2: 0 | D2: 0.4
A3: Boleto | B3: 1.99 | C3: 0 | D3: 0.3
A4: Cartão de Crédito (à vista) | B4: 0.35 | C4: 0.0189 | D4: 0.2
A5: Cartão de Crédito (parcelado) | B5: 0.49 | C5: 0.045 | D5: 0.1
A10: Resumo
A11: Uso Total | D11: =SUM(D2:D8) -> 1
A12: Taxa Fixa Média Ponderada | B12: =SUMPRODUCT(B2:B8, D2:D8) -> 1.512
A13: Taxa Variável Média Ponderada | C13: =SUMPRODUCT(C2:C8, D2:D8) -> 0.00828
